<list>
  <contact>
    <name>Bartek</name>
    <id>bartek</id>
  </contact>
  <contact>
    <name>Dominika</name>
    <id>misia</id>
  </contact>
  <contact>
    <name>Użytkownik 2</name>
    <id>2</id>
  </contact>
  <contact>
    <name>Użytkownik 3</name>
    <id>3</id>
  </contact>
  <contact>
    <name>Użytkownik 4</name>
    <id>4</id>
  </contact>
  <contact>
    <name>Użytkownik 5</name>
    <id>5</id>
  </contact>
  <contact>
    <name>Użytkownik 6</name>
    <id>6</id>
  </contact>
  <contact>
    <name>Użytkownik 7</name>
    <id>7</id>
  </contact>
  <contact>
    <name>Użytkownik 8</name>
    <id>8</id>
  </contact>
  <contact>
    <name>Użytkownik 9</name>
    <id>9</id>
  </contact>
</list>